[
  {
    "id": 101,
    "name": "中枢エリア",
    "dropTable": {
      "baseEffects": ["敏捷", "筋力", "意志", "知性", "メイン能力"],
      "extraEffects": ["攻撃力", "灼熱ダメージ", "電磁ダメージ", "寒冷ダメージ", "自然ダメージ", "アーツ強度", "必殺技効率", "アーツダメージ"],
      "skillEffects": ["強攻","圧制","追襲","破砕","巧技","噴発","流回","効率"]
    }
  },
  {
    "id": 102,
    "name": "源石研究パーク",
    "dropTable": {
      "baseEffects": ["敏捷", "筋力", "意志", "知性", "メイン能力"],
      "extraEffects": ["攻撃力","物理ダメージ","電磁ダメージ","寒冷ダメージ","自然ダメージ","会心率","必殺技効率","アーツダメージ"],
      "skillEffects": ["圧制","追襲","昂揚","巧技","付術","治癒","切骨","効率"]
    }
  },
  {
    "id": 103,
    "name": "鉱山エリア",
    "dropTable": {
      "baseEffects": ["敏捷", "筋力", "意志", "知性", "メイン能力"],
      "extraEffects": ["HP","物理ダメージ","灼熱ダメージ","寒冷ダメージ","自然ダメージ","会心率","アーツ強度","回復効率"],
      "skillEffects": ["強攻","圧制","巧技","残虐","付術","噴発","夜幕","効率"]
    }
  },
  {
    "id": 104,
    "name": "エネルギー高地",
    "dropTable": {
      "baseEffects": ["敏捷", "筋力", "意志", "知性", "メイン能力"],
      "extraEffects": ["攻撃力","HP","物理ダメージ","灼熱ダメージ","自然ダメージ","会心率","アーツ強度","回復効率"],
      "skillEffects": ["追襲","破砕","昂揚","残虐","付術","治癒","切骨","流回"]
    }
  },
  {
    "id": 105,
    "name": "武陵城",
    "dropTable": {
      "baseEffects": ["敏捷", "筋力", "意志", "知性", "メイン能力"],
      "extraEffects": ["攻撃力","HP","電磁ダメージ","寒冷ダメージ","会心率","必殺技効率","アーツダメージ","回復効率"],
      "skillEffects": ["強攻","破砕","残虐","治癒","切骨","噴発","夜幕","流回"]
    }
  }
]